snlohelper/__init__.py
snlohelper/base_function.py
snlohelper/focus.py
snlohelper/functions.py
snlohelper/import_snlo_file.py
snlohelper/main_window.py
snlohelper/mix_methods.py
snlohelper/pw_opo_bb.py
snlohelper/q_mix.py
snlohelper/ref_index.py
snlohelper/snlo.py
snlohelper/two_d_cav_lp.py
snlohelper/two_d_mix_lp.py
snlohelper/two_d_mix_sp.py
snlohelper/utils.py
snlo_helper-0.4.0.dist-info/LICENSE
snlo_helper-0.4.0.dist-info/METADATA
snlo_helper-0.4.0.dist-info/WHEEL
snlo_helper-0.4.0.dist-info/top_level.txt
snlo_helper-0.4.0.dist-info/RECORD
