Metadata-Version: 2.1
Name: snlo-helper
Version: 0.4.0
Summary: An autoclicker to automatically configure and read SNLO.
Author: Benedikt Burger
Project-URL: Repository, https://github.com/BenediktBurger/snlo-helper
Project-URL: Issues, https://github.com/BenediktBurger/snlo-helper/issues
Keywords: SNLO,nonlinear optics,simulation
Classifier: Development Status :: 4 - Beta
Classifier: Intended Audience :: Science/Research
Classifier: Topic :: Scientific/Engineering :: Physics
Classifier: Topic :: Utilities
Requires-Python: >=3.9
License-File: LICENSE
Requires-Dist: pyautogui
Requires-Dist: pyperclip
Provides-Extra: full
Requires-Dist: numpy ; extra == 'full'
